gcp_compute_machines/__init__.py
gcp_compute_machines/constants.py
gcp_compute_machines/exceptions.py
gcp_compute_machines/providers/__init__.py
gcp_compute_machines/providers/base/__init__.py
gcp_compute_machines/providers/base/base_machines_provider.py
gcp_compute_machines/providers/base/models/__init__.py
gcp_compute_machines/providers/base/models/base_machine_info_model.py
gcp_compute_machines/providers/base/models/helper_types.py
gcp_compute_machines/providers/gcloud_compute/__init__.py
gcp_compute_machines/providers/gcloud_compute/gcloud_compute_provider.py
gcp_compute_machines/providers/gcloud_compute/models/__init__.py
gcp_compute_machines/providers/gcloud_compute/models/gcloud_compute_machine_info_model.py
gcp_compute_machines/providers/scraper/__init__.py
gcp_compute_machines/providers/scraper/mappings/accelerator-optimized-machines-sku.yaml
gcp_compute_machines/providers/scraper/mappings/accelerator-optimized-machines.csv
gcp_compute_machines/providers/scraper/mappings/compute-optimized-machines-sku.yaml
gcp_compute_machines/providers/scraper/mappings/compute-optimized-machines.csv
gcp_compute_machines/providers/scraper/mappings/general-purpose-machines-sku.yaml
gcp_compute_machines/providers/scraper/mappings/general-purpose-machines.csv
gcp_compute_machines/providers/scraper/mappings/gpu-skus-mapping.yaml
gcp_compute_machines/providers/scraper/mappings/memory-optimized-machines-sku.yaml
gcp_compute_machines/providers/scraper/mappings/memory-optimized-machines.csv
gcp_compute_machines/providers/scraper/mappings/storage-optimized-machines-sku.yaml
gcp_compute_machines/providers/scraper/mappings/storage-optimized-machines.csv
gcp_compute_machines/providers/scraper/mappings/storage-skus-mapping.yaml
gcp_compute_machines/providers/scraper/mappings/todo.md
gcp_compute_machines/providers/scraper/models/__init__.py
gcp_compute_machines/providers/scraper/models/machine_info_model.py
gcp_compute_machines/providers/scraper/models/skus/__init__.py
gcp_compute_machines-0.1.1.dist-info/LICENSE
gcp_compute_machines-0.1.1.dist-info/METADATA
gcp_compute_machines-0.1.1.dist-info/WHEEL
gcp_compute_machines-0.1.1.dist-info/RECORD
