Metadata-Version: 2.1
Name: gcp_compute_machines
Version: 0.1.1
Summary: A python package for scraping and exporting GCP Compute Machines metadata and costs information.
Home-page: https://github.com/vbutoma/gcp-compute-machines-costs
License: Apache-2.0
Keywords: gcp,google-compute-machines,google-compute-machines-costs
Author: Vitaly
Author-email: vit.butoma@gmail.com
Requires-Python: >=3.12,<4.0
Classifier: License :: OSI Approved :: Apache Software License
Classifier: Programming Language :: Python :: 3
Classifier: Programming Language :: Python :: 3.12
Requires-Dist: google-cloud-billing (>=1.15.0,<2.0.0)
Requires-Dist: google-cloud-compute (>=1.23.0,<2.0.0)
Requires-Dist: loguru (>=0.7.2,<0.8.0)
Requires-Dist: lxml (>=5.3.0,<6.0.0)
Requires-Dist: pandas (>=2.2.3,<3.0.0)
Requires-Dist: pydantic (>=2.6.4,<3.0.0)
Requires-Dist: pyyaml (>=6.0.1,<7.0.0)
Project-URL: Repository, https://github.com/vbutoma/gcp-compute-machines-costs
